deltae/__init__.py
deltae-1.1.2.dist-info/WHEEL
deltae-1.1.2.dist-info/METADATA
deltae-1.1.2.dist-info/RECORD
