Metadata-Version: 2.1
Name: deltae
Version: 1.1.2
Summary: Deltae 2000 written in pure python. See README.md for more
Home-page: https://pypi.org/project/deltae/
License: MIT
Keywords: color difference,colour difference,delta e
Author: Kaine Bruce
Author-email: kaineyb@gmail.com
Requires-Python: >=3.6,<4.0
Classifier: License :: OSI Approved :: MIT License
Classifier: Programming Language :: Python :: 3
Classifier: Programming Language :: Python :: 3.10
Classifier: Programming Language :: Python :: 3.6
Classifier: Programming Language :: Python :: 3.7
Classifier: Programming Language :: Python :: 3.8
Classifier: Programming Language :: Python :: 3.9
Project-URL: Repository, https://github.com/kaineyb/deltae
